codepathfinder/__init__.py
codepathfinder/config.py
codepathfinder/dataflow.py
codepathfinder/decorators.py
codepathfinder/ir.py
codepathfinder/logic.py
codepathfinder/matchers.py
codepathfinder/presets.py
codepathfinder/propagation.py
codepathfinder/bin/pathfinder
codepathfinder/cli/__init__.py
codepathfinder-1.3.3.dist-info/licenses/LICENSE
rules/__init__.py
rules/container_combinators.py
rules/container_decorators.py
rules/container_ir.py
rules/container_matchers.py
rules/container_programmatic.py
rules/python_decorators.py
rules/python_ir.py
rules/python/__init__.py
rules/python/deserialization/__init__.py
rules/python/deserialization/pickle_loads.py
rules/python/django/__init__.py
rules/python/django/sql_injection.py
rules/python/flask/__init__.py
rules/python/flask/debug_mode.py
rules/python/injection/__init__.py
codepathfinder-1.3.3.dist-info/METADATA
codepathfinder-1.3.3.dist-info/WHEEL
codepathfinder-1.3.3.dist-info/entry_points.txt
codepathfinder-1.3.3.dist-info/top_level.txt
codepathfinder-1.3.3.dist-info/RECORD
