Metadata-Version: 2.4
Name: codepathfinder
Version: 1.3.3
Summary: Python SDK for code-pathfinder static analysis for modern security teams
Home-page: https://github.com/shivasurya/code-pathfinder
Author: code-pathfinder contributors
License: AGPL-3.0
Project-URL: Homepage, https://codepathfinder.dev
Project-URL: Repository, https://github.com/shivasurya/code-pathfinder
Project-URL: Documentation, https://codepathfinder.dev
Keywords: sast,security,static-analysis,codeql-alternative
Classifier: Development Status :: 4 - Beta
Classifier: Intended Audience :: Developers
Classifier: License :: OSI Approved :: GNU Affero General Public License v3
Classifier: Programming Language :: Python :: 3
Classifier: Programming Language :: Python :: 3.8
Classifier: Programming Language :: Python :: 3.9
Classifier: Programming Language :: Python :: 3.10
Classifier: Programming Language :: Python :: 3.11
Classifier: Programming Language :: Python :: 3.12
Classifier: Topic :: Security
Classifier: Topic :: Software Development :: Testing
Requires-Python: >=3.8
License-File: LICENSE
Provides-Extra: dev
Requires-Dist: pytest>=7.0.0; extra == "dev"
Requires-Dist: pytest-cov>=4.0.0; extra == "dev"
Requires-Dist: black>=23.0.0; extra == "dev"
Requires-Dist: mypy>=1.0.0; extra == "dev"
Requires-Dist: ruff>=0.1.0; extra == "dev"
Dynamic: home-page
Dynamic: license-file
Dynamic: requires-python
